deploy/__init__.py
deploy/admin.py
deploy/apps.py
deploy/models.py
deploy/tests.py
deploy/views.py
deploy/migrations/__init__.py
django_deploy_asgi-1.0.1.dist-info/LICENSE
django_deploy_asgi-1.0.1.dist-info/METADATA
django_deploy_asgi-1.0.1.dist-info/WHEEL
django_deploy_asgi-1.0.1.dist-info/top_level.txt
django_deploy_asgi-1.0.1.dist-info/RECORD
