Metadata-Version: 2.1
Name: django-deploy-asgi
Version: 1.0.1
Summary: Easy to use django command for deploy your project in nginx using asgi.
Home-page: https://github.com/n4b3ts3/django-deploy
Author: Esteban Chacon Martin
Author-email: n4b3ts3@gmail.com
License: UNKNOWN
Project-URL: Bug Tracker, https://github.com/n4b3ts3/django-deploy/issues
Keywords: deploy,django,nginx,asgi
Platform: UNKNOWN
Classifier: Framework :: Django
Classifier: Programming Language :: Python :: 3
Classifier: Operating System :: POSIX :: Linux
Classifier: License :: OSI Approved :: GNU General Public License (GPL)
Requires-Python: >=3.6
License-File: LICENSE
